cfgstack/__init__.py
cfgstack/cfgstack.py
cfgstack-0.2.post5.dist-info/LICENSE
cfgstack-0.2.post5.dist-info/METADATA
cfgstack-0.2.post5.dist-info/WHEEL
cfgstack-0.2.post5.dist-info/RECORD
