Metadata-Version: 2.3
Name: cfgstack
Version: 0.2.post5
Summary: Load stacks of JSON, TOML or YAML data
License: GPL-3.0-only
Keywords: configfile,file stacks,reference trees
Author: J C Lawrence
Author-email: claw@kanga.nu
Requires-Python: >=3.8,<4.0
Classifier: License :: OSI Approved :: GNU General Public License v3 (GPLv3)
Classifier: Programming Language :: Python :: 3
Classifier: Programming Language :: Python :: 3.8
Classifier: Programming Language :: Python :: 3.9
Classifier: Programming Language :: Python :: 3.10
Classifier: Programming Language :: Python :: 3.11
Classifier: Programming Language :: Python :: 3.12
Classifier: Programming Language :: Python :: 3.13
Requires-Dist: addict (>=2.4.0,<3.0.0)
Requires-Dist: findfile_path (>=0.2.post1)
Requires-Dist: logtool (>=0.4.post1)
Requires-Dist: path (>=16.14.0)
Requires-Dist: poetry-dynamic-versioning (>=1.8.2,<2.0.0)
Requires-Dist: pyyaml (>=6.0.1,<7.0.0)
Requires-Dist: toml (>=0.10.2,<0.11.0)
Project-URL: Repository, https://github.com/clearclaw/cfgstack
